[{
        "title": "激战2",
        "imgurl": "../img/goods1.jpg",
        "price": "18",
        "code": "abc1",
        "disc": "史诗级单人传奇"
    },
    {
        "title": "梦三国2",
        "imgurl": "../img/goods2.jpg",
        "price": "46",
        "code": "abc2",
        "disc": "演绎三国传奇"

    },
    {
        "title": "永恒之塔",
        "imgurl": "../img/goods3.jpg",
        "price": "66",
        "code": "abc3",
        "disc": "暴风之地纷争再起，天魔对峙再战龙界！"
    },
    {
        "title": "枪火重生",
        "imgurl": "../img/goods4.jpg",
        "price": "24",
        "code": "abc4",
        "disc": "枪林弹火中体验冲刺的魅力！"
    }
]